<annotation>
	<folder>train</folder>
	<filename>DSC_1114.jpg</filename>
	<path>/home/prudhvi/objDetection/train/DSC_1114.jpg</path>
	<source>
		<database>Unknown</database>
	</source>
	<size>
		<width>903</width>
		<height>600</height>
		<depth>3</depth>
	</size>
	<segmented>0</segmented>
	<object>
		<name>amma</name>
		<pose>Unspecified</pose>
		<truncated>0</truncated>
		<difficult>0</difficult>
		<bndbox>
			<xmin>206</xmin>
			<ymin>238</ymin>
			<xmax>287</xmax>
			<ymax>333</ymax>
		</bndbox>
	</object>
	<object>
		<name>dad</name>
		<pose>Unspecified</pose>
		<truncated>0</truncated>
		<difficult>0</difficult>
		<bndbox>
			<xmin>278</xmin>
			<ymin>205</ymin>
			<xmax>342</xmax>
			<ymax>293</ymax>
		</bndbox>
	</object>
</annotation>
