<annotation>
	<folder>train</folder>
	<filename>IMG-20190323-WA0020.jpg</filename>
	<path>/home/prudhvi/objDetection/train/IMG-20190323-WA0020.jpg</path>
	<source>
		<database>Unknown</database>
	</source>
	<size>
		<width>899</width>
		<height>600</height>
		<depth>3</depth>
	</size>
	<segmented>0</segmented>
	<object>
		<name>bharath</name>
		<pose>Unspecified</pose>
		<truncated>0</truncated>
		<difficult>0</difficult>
		<bndbox>
			<xmin>468</xmin>
			<ymin>293</ymin>
			<xmax>514</xmax>
			<ymax>332</ymax>
		</bndbox>
	</object>
	<object>
		<name>dad</name>
		<pose>Unspecified</pose>
		<truncated>0</truncated>
		<difficult>0</difficult>
		<bndbox>
			<xmin>560</xmin>
			<ymin>184</ymin>
			<xmax>592</xmax>
			<ymax>224</ymax>
		</bndbox>
	</object>
</annotation>
